wpodnet/__init__.py
wpodnet/backend.py
wpodnet/model.py
wpodnet_pytorch-1.1.1.dist-info/licenses/LICENSE
wpodnet_pytorch-1.1.1.dist-info/METADATA
wpodnet_pytorch-1.1.1.dist-info/WHEEL
wpodnet_pytorch-1.1.1.dist-info/top_level.txt
wpodnet_pytorch-1.1.1.dist-info/RECORD
