Metadata-Version: 2.4
Name: wpodnet-pytorch
Version: 1.1.1
Summary: The implementation of ECCV 2018 paper "License Plate Detection and Recognition in Unconstrained Scenarios" in PyTorch
Author: Pandede
Maintainer: Pandede
Project-URL: Source, https://github.com/Pandede/WPODNet-Pytorch
Keywords: python,ai,computer-vision,deep-learning,torch,object-detection,license-plate-recognition,wpod,wpod-net
Classifier: Development Status :: 4 - Beta
Classifier: Intended Audience :: Developers
Classifier: Intended Audience :: Education
Classifier: Intended Audience :: Science/Research
Classifier: Programming Language :: Python :: 3
Classifier: Programming Language :: Python :: 3.6
Classifier: Programming Language :: Python :: 3.7
Classifier: Programming Language :: Python :: 3.8
Classifier: Programming Language :: Python :: 3.9
Classifier: Programming Language :: Python :: 3.10
Classifier: Programming Language :: Python :: 3.11
Classifier: Topic :: Software Development
Classifier: Topic :: Scientific/Engineering
Classifier: Topic :: Scientific/Engineering :: Artificial Intelligence
Classifier: Topic :: Scientific/Engineering :: Image Recognition
Classifier: Operating System :: POSIX :: Linux
Classifier: Operating System :: MacOS
Classifier: Operating System :: Microsoft :: Windows
Requires-Python: >=3.8
License-File: LICENSE
Requires-Dist: numpy
Requires-Dist: Pillow
Requires-Dist: torch
Requires-Dist: torchvision
Provides-Extra: test
Requires-Dist: pytest; extra == "test"
Requires-Dist: pytest-cov; extra == "test"
Requires-Dist: pooch; extra == "test"
Dynamic: license-file
